MANIFEST.in
README.txt
setup.py
docs/HISTORY.txt
docs/INSTALL.txt
docs/LICENSE.GPL
docs/LICENSE.txt
ewb_case/__init__.py
ewb_case/__init__.pyc
ewb_case.portlet.get_involved.egg-info/PKG-INFO
ewb_case.portlet.get_involved.egg-info/SOURCES.txt
ewb_case.portlet.get_involved.egg-info/dependency_links.txt
ewb_case.portlet.get_involved.egg-info/entry_points.txt
ewb_case.portlet.get_involved.egg-info/namespace_packages.txt
ewb_case.portlet.get_involved.egg-info/not-zip-safe
ewb_case.portlet.get_involved.egg-info/requires.txt
ewb_case.portlet.get_involved.egg-info/top_level.txt
ewb_case/portlet/__init__.py
ewb_case/portlet/__init__.pyc
ewb_case/portlet/get_involved/__init__.py
ewb_case/portlet/get_involved/__init__.pyc
ewb_case/portlet/get_involved/configure.zcml
ewb_case/portlet/get_involved/get_involved.py
ewb_case/portlet/get_involved/interfaces.py
ewb_case/portlet/get_involved/profiles.zcml
ewb_case/portlet/get_involved/version.txt
ewb_case/portlet/get_involved/profiles/default/metadata.xml
ewb_case/portlet/get_involved/profiles/default/portlets.xml
ewb_case/portlet/get_involved/resources/.DS_Store
ewb_case/portlet/get_involved/resources/join.png
ewb_case/portlet/get_involved/resources/join.svg
ewb_case/portlet/get_involved/resources/mentor.png
ewb_case/portlet/get_involved/resources/mentor.svg
ewb_case/portlet/get_involved/resources/sponsor.png
ewb_case/portlet/get_involved/resources/sponsor.svg
ewb_case/portlet/get_involved/templates/get_involved.pt
ewb_case/portlet/get_involved/tests/__init__.py
ewb_case/portlet/get_involved/tests/base.py
ewb_case/portlet/get_involved/tests/test_portlet.py