Metadata-Version: 1.0
Name: ewb-case.portlet.get-involved
Version: 0.1.1
Summary: Static portlet showing ways to get involved in EWB Case.
Home-page: http://github.com/mattbierner/ewb_case.portlet.get_involved/
Author: Matt Bierner
Author-email: mattbierner@gmail.com
License: GPL
Platform: UNKNOWN
Classifier: Framework :: Plone
Classifier: Programming Language :: Python
Classifier: Development Status :: 4 - Beta
